<dyo id="1"><item id="2"><productid type="number">5</productid><type type="string">Headstone</type><name type="string">Bronze Plaque - Black - Lugs with Studs</name><border type="string">Border 1</border><shape_url type="string">shapes/photos/border1.svg</shape_url><fixingSystem type="number">2</fixingSystem><shape type="string">Square</shape><color type="string">#000000</color><fixed type="number">0</fixed><texture type="string">src/bronzes/phoenix/l/01.jpg</texture><price type="number">936.94</price><quantity type="number">1</quantity><width type="number">380</width><height type="number">230</height><_length type="number">1</_length><init_width type="number">1360</init_width><init_height type="number">535</init_height><mode type="string">2d</mode><backgroundOption type="string">undefined</backgroundOption></item><item id="3"><productid type="string">78</productid><name type="string">Inscription (Bronze)</name><type type="string">Inscription</type><part type="string">Headstone</part><side type="string">Front</side><price type="number">0</price><quantity type="number">14</quantity><label type="string">RICHARD JOSEPH</label><font type="string">46.122633411696086px Arial</font><font_size type="number">28</font_size><font_family type="string">Arial</font_family><color type="string">#ffb35a</color><colorName type="string">Paint Fill</colorName><x type="number">-35.04726359687356</x><y type="number">-99.70747197006858</y><rotation type="number">0</rotation><flipx type="number">1</flipx><flipy type="number">1</flipy><height type="number">21</height><itemID type="number">2</itemID></item><item id="4"><productid type="string">78</productid><name type="string">Inscription (Bronze)</name><type type="string">Inscription</type><part type="string">Headstone</part><side type="string">Front</side><price type="number">0</price><quantity type="number">10</quantity><label type="string">O&amp;apos;SULLIVAN</label><font type="string">46.122633411696086px Arial</font><font_size type="number">28</font_size><font_family type="string">Arial</font_family><color type="string">#ffb35a</color><colorName type="string">Paint Fill</colorName><x type="number">-17.50042098509607</x><y type="number">-42.144510845421394</y><rotation type="number">0</rotation><flipx type="number">1</flipx><flipy type="number">1</flipy><height type="number">21</height><itemID type="number">3</itemID></item><item id="5"><productid type="string">78</productid><name type="string">Inscription (Bronze)</name><type type="string">Inscription</type><part type="string">Headstone</part><side type="string">Front</side><price type="number">0</price><quantity type="number">19</quantity><label type="string">In Loving Memory Of</label><font type="string">26.35579052096919px Lucida Calligraphy</font><font_size type="number">16</font_size><font_family type="string">Lucida Calligraphy</font_family><color type="string">#ffb35a</color><colorName type="string">Paint Fill</colorName><x type="number">-9.898737044710742</x><y type="number">-141.99566806692738</y><rotation type="number">0</rotation><flipx type="number">1</flipx><flipy type="number">1</flipy><height type="number">18</height><itemID type="number">6</itemID></item><item id="6"><productid type="string">78</productid><name type="string">Inscription (Bronze)</name><type type="string">Inscription</type><part type="string">Headstone</part><side type="string">Front</side><price type="number">0</price><quantity type="number">21</quantity><label type="string">10 JAN 1946 - 8 APRIL 2019</label><font type="string">37.88644887389321px Garamond</font><font_size type="number">23</font_size><font_family type="string">Garamond</font_family><color type="string">#ffb35a</color><colorName type="string">Paint Fill</colorName><x type="number">-11.892001283168725</x><y type="number">9.277037778162253</y><rotation type="number">0</rotation><flipx type="number">1</flipx><flipy type="number">1</flipy><height type="number">21</height><itemID type="number">4</itemID></item><item id="7"><productid type="string">78</productid><name type="string">Inscription (Bronze)</name><type type="string">Inscription</type><part type="string">Headstone</part><side type="string">Front</side><price type="number">0</price><quantity type="number">14</quantity><label type="string">Forever Missed</label><font type="string">34.591975058772064px Great Vibes</font><font_size type="number">21</font_size><font_family type="string">Great Vibes</font_family><color type="string">#ffb35a</color><colorName type="string">Paint Fill</colorName><x type="number">-179.52158350599427</x><y type="number">115.30747197006832</y><rotation type="number">0</rotation><flipx type="number">1</flipx><flipy type="number">1</flipy><height type="number">21</height><itemID type="number">7</itemID></item><item id="8"><productid type="string">78</productid><name type="string">Inscription (Bronze)</name><type type="string">Inscription</type><part type="string">Headstone</part><side type="string">Front</side><price type="number">0</price><quantity type="number">25</quantity><label type="string">Love You Wherever You Are</label><font type="string">32.94473815121149px Lucida Calligraphy</font><font_size type="number">20</font_size><font_family type="string">Lucida Calligraphy</font_family><color type="string">#ffb35a</color><colorName type="string">Paint Fill</colorName><x type="number">-3.3991580298070403</x><y type="number">68.14300191296695</y><rotation type="number">0</rotation><flipx type="number">1</flipx><flipy type="number">1</flipy><height type="number">21</height><itemID type="number">5</itemID></item><item id="9"><productid type="string">78</productid><name type="string">Inscription (Bronze)</name><type type="string">Inscription</type><part type="string">Headstone</part><side type="string">Front</side><price type="number">0</price><quantity type="number">34</quantity><label type="string">by Sonia &amp;  his Brothers &amp; Sisters</label><font type="string">29.650264336090338px Great Vibes</font><font_size type="number">18</font_size><font_family type="string">Great Vibes</font_family><color type="string">#ffb35a</color><colorName type="string">Paint Fill</colorName><x type="number">84.63884389494604</x><y type="number">142.78312304363027</y><rotation type="number">0</rotation><flipx type="number">1</flipx><flipy type="number">1</flipy><height type="number">21</height><itemID type="number">8</itemID></item></dyo>