<dyo id="1"><item id="2"><productid type="number">34</productid><type type="string">Headstone</type><name type="string">Square</name><shape type="string">Square</shape><color type="string">#000000</color><fixed type="number">0</fixed><texture type="string">src/granites/forever2/l/17.jpg</texture><price type="number">360.02</price><quantity type="number">1</quantity><width type="number">284</width><height type="number">157</height><_length type="number">1</_length><init_width type="number">1277</init_width><init_height type="number">630</init_height><backgroundOption type="string">undefined</backgroundOption><device type="string">desktop</device><dpr type="number">0.8999999761581421</dpr><orientation type="string">landscape</orientation><version type="number">136</version><version_date type="number">20210324</version_date><mode type="string">2d</mode></item><item id="3"><productid type="string">125</productid><name type="string">Inscription (Traditional Engraved)</name><type type="string">Inscription</type><part type="string">Headstone</part><side type="string">Front</side><price type="number">3</price><quantity type="number">17</quantity><label type="string">21/11/93–19/11/20</label><font type="string">36.98477014699873px Garamond</font><font_size type="number">19</font_size><font_family type="string">Garamond</font_family><color type="string">#ffffff</color><colorName type="string">Standard</colorName><x type="number">0.8997674826758839</x><y type="number">-39.65396825396826</y><rotation type="number">0</rotation><flipx type="number">1</flipx><flipy type="number">1</flipy><height type="number">14</height><itemID type="number">2</itemID></item><item id="4"><productid type="string">125</productid><name type="string">Inscription (Traditional Engraved)</name><type type="string">Inscription</type><part type="string">Headstone</part><side type="string">Front</side><price type="number">3.75</price><quantity type="number">23</quantity><label type="string">Devoted Dad to Ella &amp; Olivia</label><font type="string">40.8779038466828px Garamond</font><font_size type="number">21</font_size><font_family type="string">Garamond</font_family><color type="string">#c99d44</color><colorName type="string">Gold Gilding</colorName><x type="number">-2.4993543039328188</x><y type="number">2.991534637381619</y><rotation type="number">0</rotation><flipx type="number">1</flipx><flipy type="number">1</flipy><height type="number">15</height><itemID type="number">7</itemID></item><item id="5"><productid type="string">125</productid><name type="string">Inscription (Traditional Engraved)</name><type type="string">Inscription</type><part type="string">Headstone</part><side type="string">Front</side><price type="number">3.75</price><quantity type="number">14</quantity><label type="string">That bloody kid…</label><font type="string">35.038203297156684px Adorable</font><font_size type="number">18</font_size><font_family type="string">Adorable</font_family><color type="string">#c99d44</color><colorName type="string">Gold Gilding</colorName><x type="number">-129.96641760723253</x><y type="number">-127.77425382577883</y><rotation type="number">0</rotation><flipx type="number">1</flipx><flipy type="number">1</flipy><height type="number">18</height><itemID type="number">1</itemID></item><item id="6"><productid type="string">125</productid><name type="string">Inscription (Traditional Engraved)</name><type type="string">Inscription</type><part type="string">Headstone</part><side type="string">Front</side><price type="number">3.75</price><quantity type="number">30</quantity><label type="string">A lovable larakin connecting us all</label><font type="string">35.038203297156684px Adorable</font><font_size type="number">18</font_size><font_family type="string">Adorable</font_family><color type="string">#ffffff</color><colorName type="string">Gold Gilding</colorName><x type="number">-0.09997419122566953</x><y type="number">51.708643773516485</y><rotation type="number">0</rotation><flipx type="number">1</flipx><flipy type="number">1</flipy><height type="number">18</height><itemID type="number">6</itemID></item><item id="7"><productid type="string">125</productid><name type="string">Inscription (Traditional Engraved)</name><type type="string">Inscription</type><part type="string">Headstone</part><side type="string">Front</side><price type="number">3.75</price><quantity type="number">27</quantity><label type="string">He is here &amp; will always be around</label><font type="string">35.038203297156684px Adorable</font><font_size type="number">18</font_size><font_family type="string">Adorable</font_family><color type="string">#ffffff</color><colorName type="string">Gold Gilding</colorName><x type="number">1.0997158651276777</x><y type="number">87.84479998121924</y><rotation type="number">0</rotation><flipx type="number">1</flipx><flipy type="number">1</flipy><height type="number">18</height><itemID type="number">4</itemID></item><item id="8"><productid type="string">125</productid><name type="string">Inscription (Traditional Engraved)</name><type type="string">Inscription</type><part type="string">Headstone</part><side type="string">Front</side><price type="number">3.75</price><quantity type="number">17</quantity><label type="string">&amp; around &amp; around...</label><font type="string">35.038203297156684px Adorable</font><font_size type="number">18</font_size><font_family type="string">Adorable</font_family><color type="string">#ffffff</color><colorName type="string">Gold Gilding</colorName><x type="number">-1.7995349653518815</x><y type="number">122.6409208086551</y><rotation type="number">0</rotation><flipx type="number">1</flipx><flipy type="number">1</flipy><height type="number">17</height><itemID type="number">10</itemID></item></dyo>