<dyo id="1"><item id="2"><productid type="number">4</productid><type type="string">Headstone</type><name type="string">Headstone 31</name><shape type="string">Headstone 36</shape><color type="string">#000000</color><fixed type="number">4</fixed><texture type="string">src/granites/forever2/l/18.jpg</texture><price type="number">1546.03</price><quantity type="number">1</quantity><width type="number">490</width><height type="number">600</height><_length type="number">1</_length><init_width type="number">412</init_width><init_height type="number">662</init_height><mode type="string">2d</mode></item><item id="3"><productid type="number">2300</productid><id type="number">2300</id><uid type="number">1616676355612</uid><path type="string">../upload/2021/03/</path><name type="string">Vitreous Enamel</name><type type="string">Photo</type><item type="string">../upload/2021/03/161667635561201evwnnsnjnbpq3djppeepmn.jpg</item><color type="number">0</color><mask type="number">0</mask><x type="number">126.44264174234502</x><y type="number">137.2386813882581</y><flipx type="number">1</flipx><flipy type="number">1</flipy><rotation type="number">-1</rotation><ratio type="number">0.3033987915407855</ratio><shape_url type="string">shapes/photos/oval_vertical.svg</shape_url><part type="string">Headstone</part><side type="string">Front</side><src type="string">01EVWNNSNJNBPQ3DJPPEEPMN7Q.jpg</src><price type="number">440</price><quantity type="number">1</quantity><size type="string">110 x 150 mm</size><itemID type="number">23</itemID></item><item id="4"><productid type="number">2300</productid><id type="number">2300</id><uid type="number">1616676581141</uid><path type="string">../upload/2021/03/</path><name type="string">Vitreous Enamel</name><type type="string">Photo</type><item type="string">../upload/2021/03/1616676581141fb_img_1616676491269_cro.jpg</item><color type="number">0</color><mask type="number">0</mask><x type="number">-127.30262614389838</x><y type="number">138.4637214832744</y><flipx type="number">1</flipx><flipy type="number">1</flipy><rotation type="number">0</rotation><ratio type="number">0.36407854984894256</ratio><shape_url type="string">shapes/photos/oval_vertical.svg</shape_url><part type="string">Headstone</part><side type="string">Front</side><src type="string">FB_IMG_1616676491269.jpg</src><price type="number">490</price><quantity type="number">1</quantity><size type="string">130 x 180 mm</size><itemID type="number">25</itemID></item><item id="5"><productid type="number">2300</productid><id type="number">2300</id><uid type="number">1616676626656</uid><path type="string">../upload/2021/03/</path><name type="string">Vitreous Enamel</name><type type="string">Photo</type><item type="string">../upload/2021/03/1616676626656fb_img_1616676530640_cro.jpg</item><color type="number">0</color><mask type="number">0</mask><x type="number">44.40888516668235</x><y type="number">137.09907465108847</y><flipx type="number">1</flipx><flipy type="number">1</flipy><rotation type="number">0</rotation><ratio type="number">0.36407854984894256</ratio><shape_url type="string">shapes/photos/oval_vertical.svg</shape_url><part type="string">Headstone</part><side type="string">Front</side><src type="string">FB_IMG_1616676530640.jpg</src><price type="number">490</price><quantity type="number">1</quantity><size type="string">130 x 180 mm</size><itemID type="number">26</itemID></item><item id="6"><productid type="number">2300</productid><id type="number">2300</id><uid type="number">1616676953899</uid><path type="string">../upload/2021/03/</path><name type="string">Vitreous Enamel</name><type type="string">Photo</type><item type="string">../upload/2021/03/1616676953899fb_img_1616676944472_cro.jpg</item><color type="number">0</color><mask type="number">0</mask><x type="number">-42.98336960993035</x><y type="number">133.97539396488355</y><flipx type="number">1</flipx><flipy type="number">1</flipy><rotation type="number">0</rotation><ratio type="number">0.36407854984894256</ratio><shape_url type="string">shapes/photos/oval_vertical.svg</shape_url><part type="string">Headstone</part><side type="string">Front</side><src type="string">FB_IMG_1616676944472.jpg</src><price type="number">490</price><quantity type="number">1</quantity><size type="string">130 x 180 mm</size><itemID type="number">27</itemID></item><item id="7"><productid type="string">71</productid><name type="string">Black Granite Motif (free)</name><type type="string">Motif</type><part type="string">Headstone</part><side type="string">Front</side><src type="string">1_155_14</src><item type="string">1_155_14</item><price type="number">0</price><quantity type="number">1</quantity><color type="string">#ffffff</color><colorName type="string">Standard</colorName><x type="number">3.0037448788171446</x><y type="number">-169.37135578980093</y><flipx type="number">1</flipx><flipy type="number">1</flipy><rotation type="number">0</rotation><height type="number">87</height><ratio type="number">0.13942307692307693</ratio><itemID type="number">28</itemID></item><item id="8"><productid type="string">71</productid><name type="string">Black Granite Motif (free)</name><type type="string">Motif</type><part type="string">Headstone</part><side type="string">Front</side><src type="string">butterfly_004</src><item type="string">butterfly_004</item><price type="number">0</price><quantity type="number">1</quantity><color type="string">#ffffff</color><colorName type="string">Standard</colorName><x type="number">67.78643118736801</x><y type="number">-160.69215723368993</y><flipx type="number">1</flipx><flipy type="number">1</flipy><rotation type="number">0</rotation><height type="number">61</height><ratio type="number">0.03511801957397812</ratio><itemID type="number">30</itemID></item><item id="9"><productid type="string">71</productid><name type="string">Black Granite Motif (free)</name><type type="string">Motif</type><part type="string">Headstone</part><side type="string">Front</side><src type="string">butterfly_028</src><item type="string">butterfly_028</item><price type="number">0</price><quantity type="number">1</quantity><color type="string">#ffffff</color><colorName type="string">Standard</colorName><x type="number">-61.62748592102551</x><y type="number">-166.2438293245538</y><flipx type="number">1</flipx><flipy type="number">1</flipy><rotation type="number">0</rotation><height type="number">52</height><ratio type="number">0.029936672423719057</ratio><itemID type="number">31</itemID></item><item id="10"><productid type="string">16</productid><name type="string">Black Granite Inscription (free)</name><type type="string">Inscription</type><part type="string">Headstone</part><side type="string">Front</side><price type="number">0</price><quantity type="number">1</quantity><label type="string">In Loving Memories</label><font type="string">32.8055px Chopin Script</font><font_size type="number">49</font_size><font_family type="string">Chopin Script</font_family><color type="string">#ffffff</color><colorName type="string">Standard</colorName><x type="number">-11.927027592352204</x><y type="number">-116.77126048673776</y><rotation type="number">0</rotation><flipx type="number">1</flipx><flipy type="number">1</flipy><height type="number">57</height><itemID type="number">12</itemID></item><item id="11"><productid type="string">16</productid><name type="string">Black Granite Inscription (free)</name><type type="string">Inscription</type><part type="string">Headstone</part><side type="string">Front</side><price type="number">0</price><quantity type="number">30</quantity><label type="string">Of</label><font type="string">31.4665px Chopin Script</font><font_size type="number">47</font_size><font_family type="string">Chopin Script</font_family><color type="string">#ffffff</color><colorName type="string">Standard</colorName><x type="number">-2.715536209974374</x><y type="number">-92.5471168393363</y><rotation type="number">0</rotation><flipx type="number">1</flipx><flipy type="number">1</flipy><height type="number">48</height><itemID type="number">15</itemID></item><item id="12"><productid type="string">16</productid><name type="string">Black Granite Inscription (free)</name><type type="string">Inscription</type><part type="string">Headstone</part><side type="string">Front</side><price type="number">0</price><quantity type="number">1</quantity><label type="string">And</label><font type="string">36.8225px Chopin Script</font><font_size type="number">55</font_size><font_family type="string">Chopin Script</font_family><color type="string">#ffffff</color><colorName type="string">Standard</colorName><x type="number">-5.6555051166380395</x><y type="number">-15.942163331637744</y><rotation type="number">0</rotation><flipx type="number">1</flipx><flipy type="number">1</flipy><height type="number">57</height><itemID type="number">17</itemID></item><item id="13"><productid type="string">16</productid><name type="string">Black Granite Inscription (free)</name><type type="string">Inscription</type><part type="string">Headstone</part><side type="string">Front</side><price type="number">0</price><quantity type="number">1</quantity><label type="string">Baby Valma Papertalk</label><font type="string">28.7885px Chopin Script</font><font_size type="number">43</font_size><font_family type="string">Chopin Script</font_family><color type="string">#ffffff</color><colorName type="string">Standard</colorName><x type="number">-7.574898544282604</x><y type="number">10.617306821837076</y><rotation type="number">0</rotation><flipx type="number">1</flipx><flipy type="number">1</flipy><height type="number">48</height><itemID type="number">18</itemID></item><item id="14"><productid type="string">16</productid><name type="string">Black Granite Inscription (free)</name><type type="string">Inscription</type><part type="string">Headstone</part><side type="string">Front</side><price type="number">0</price><quantity type="number">27</quantity><label type="string">Patrica May Slater Papertalk</label><font type="string">30.127499999999998px Chopin Script</font><font_size type="number">45</font_size><font_family type="string">Chopin Script</font_family><color type="string">#ffffff</color><colorName type="string">Standard</colorName><x type="number">0</x><y type="number">-63.16994225280166</y><rotation type="number">0</rotation><flipx type="number">1</flipx><flipy type="number">1</flipy><height type="number">48</height><itemID type="number">19</itemID></item><item id="15"><productid type="string">16</productid><name type="string">Black Granite Inscription (free)</name><type type="string">Inscription</type><part type="string">Headstone</part><side type="string">Front</side><price type="number">0</price><quantity type="number">1</quantity><label type="string">Born 17-11-1988 Sadly Passed 06-04-2017</label><font type="string">18.746px Chopin Script</font><font_size type="number">28</font_size><font_family type="string">Chopin Script</font_family><color type="string">#ffffff</color><colorName type="string">Standard</colorName><x type="number">-8.706134047592911</x><y type="number">-37.50433651471411</y><rotation type="number">0</rotation><flipx type="number">1</flipx><flipy type="number">1</flipy><height type="number">31</height><itemID type="number">20</itemID></item><item id="16"><productid type="string">16</productid><name type="string">Black Granite Inscription (free)</name><type type="string">Inscription</type><part type="string">Headstone</part><side type="string">Front</side><price type="number">0</price><quantity type="number">1</quantity><label type="string">Born 06-04-2017 Sadly Passed 06-04-2017</label><font type="string">17.407px Chopin Script</font><font_size type="number">26</font_size><font_family type="string">Chopin Script</font_family><color type="string">#ffffff</color><colorName type="string">Standard</colorName><x type="number">-12.252807234850081</x><y type="number">31.921857491568687</y><rotation type="number">0</rotation><flipx type="number">1</flipx><flipy type="number">1</flipy><height type="number">25</height><itemID type="number">21</itemID></item><item id="17"><productid type="string">16</productid><name type="string">Black Granite Inscription (free)</name><type type="string">Inscription</type><part type="string">Headstone</part><side type="string">Front</side><price type="number">0</price><quantity type="number">1</quantity><label type="string">FOREVER YOUNG</label><font type="string">24.102px Chopin Script</font><font_size type="number">36</font_size><font_family type="string">Chopin Script</font_family><color type="string">#ffffff</color><colorName type="string">Standard</colorName><x type="number">-20.61326132254584</x><y type="number">58.036095408719234</y><rotation type="number">0</rotation><flipx type="number">1</flipx><flipy type="number">1</flipy><height type="number">42</height><itemID type="number">32</itemID></item></dyo>