<dyo id="1"><item id="2"><productid type="number">9</productid><type type="string">Headstone</type><name type="string">Square</name><shape type="string">Square</shape><color type="string">#000000</color><fixed type="number">0</fixed><texture type="string">src/granites/forever2/l/18.jpg</texture><price type="number">325.22</price><quantity type="number">1</quantity><width type="number">300</width><height type="number">200</height><_length type="number">1</_length><init_width type="number">375</init_width><init_height type="number">579</init_height><backgroundOption type="string">undefined</backgroundOption><device type="string">mobile</device><dpr type="number">3</dpr><orientation type="string">portrait</orientation><version type="string">1.42</version><version_date type="number">20220630</version_date><mode type="string">2d</mode><navigator type="string">iPhone, Apple Computer, Inc., Mozilla/5.0 (iPhone; CPU iPhone OS 15_5 like Mac OS X) AppleWebKit/605.1.15 (KHTML, like Gecko) Version/15.5 Mobile/15E148 Safari/604.1, 375x812</navigator></item><item id="3"><productid type="string">16</productid><name type="string">Black Granite Inscription (free)</name><type type="string">Inscription</type><part type="string">Headstone</part><side type="string">Front</side><price type="number">0</price><quantity type="number">5</quantity><label type="string">Shady</label><font type="string">193.78125px Chopin Script</font><font_size type="number">53</font_size><font_family type="string">Chopin Script</font_family><color type="string">#ffffff</color><colorName type="string">Paint Fill</colorName><x type="number">-216</x><y type="number">-255</y><rotation type="number">0</rotation><flipx type="number">1</flipx><flipy type="number">1</flipy><height type="number">54</height><itemID type="number">2</itemID></item><item id="4"><productid type="string">16</productid><name type="string">Black Granite Inscription (free)</name><type type="string">Inscription</type><part type="string">Headstone</part><side type="string">Front</side><price type="number">0</price><quantity type="number">8</quantity><label type="string">(Choppy)</label><font type="string">62.15625px Chopin Script</font><font_size type="number">17</font_size><font_family type="string">Chopin Script</font_family><color type="string">#ffffff</color><colorName type="string">Paint Fill</colorName><x type="number">-222</x><y type="number">-152</y><rotation type="number">0</rotation><flipx type="number">1</flipx><flipy type="number">1</flipy><height type="number">20</height><itemID type="number">3</itemID></item><item id="5"><productid type="string">16</productid><name type="string">Black Granite Inscription (free)</name><type type="string">Inscription</type><part type="string">Headstone</part><side type="string">Front</side><price type="number">0</price><quantity type="number">14</quantity><label type="string">Love and miss you</label><font type="string">73.125px Chopin Script</font><font_size type="number">20</font_size><font_family type="string">Chopin Script</font_family><color type="string">#ffffff</color><colorName type="string">Paint Fill</colorName><x type="number">-288</x><y type="number">107</y><rotation type="number">0</rotation><flipx type="number">1</flipx><flipy type="number">1</flipy><height type="number">22</height><itemID type="number">4</itemID></item><item id="6"><productid type="string">16</productid><name type="string">Black Granite Inscription (free)</name><type type="string">Inscription</type><part type="string">Headstone</part><side type="string">Front</side><price type="number">0</price><quantity type="number">23</quantity><label type="string">every day you’re not with me</label><font type="string">73.125px Chopin Script</font><font_size type="number">20</font_size><font_family type="string">Chopin Script</font_family><color type="string">#ffffff</color><colorName type="string">Paint Fill</colorName><x type="number">-192</x><y type="number">178</y><rotation type="number">0</rotation><flipx type="number">1</flipx><flipy type="number">1</flipy><height type="number">19</height><itemID type="number">5</itemID></item><item id="7"><productid type="string">16</productid><name type="string">Black Granite Inscription (free)</name><type type="string">Inscription</type><part type="string">Headstone</part><side type="string">Front</side><price type="number">0</price><quantity type="number">8</quantity><label type="string">my puppta</label><font type="string">73.125px Chopin Script</font><font_size type="number">20</font_size><font_family type="string">Chopin Script</font_family><color type="string">#ffffff</color><colorName type="string">Paint Fill</colorName><x type="number">-222</x><y type="number">252.66666666666674</y><rotation type="number">0</rotation><flipx type="number">1</flipx><flipy type="number">1</flipy><height type="number">17</height><itemID type="number">6</itemID></item><item id="8"><productid type="string">16</productid><name type="string">Black Granite Inscription (free)</name><type type="string">Inscription</type><part type="string">Headstone</part><side type="string">Front</side><price type="number">0</price><quantity type="number">21</quantity><label type="string">31/10/2005 - 30/06/2020</label><font type="string">51.1875px Garamond</font><font_size type="number">14</font_size><font_family type="string">Garamond</font_family><color type="string">#ffffff</color><colorName type="string">Paint Fill</colorName><x type="number">-231</x><y type="number">-36</y><rotation type="number">0</rotation><flipx type="number">1</flipx><flipy type="number">1</flipy><height type="number">10</height><itemID type="number">7</itemID></item><item id="9"><productid type="number">60</productid><name type="string">Motif (Laser)</name><type type="string">Motif</type><part type="string">Headstone</part><side type="string">Front</side><src type="string">1_037_10</src><item type="string">1_037_10</item><price type="number">0</price><quantity type="number">1</quantity><color type="string">#ffffff</color><colorName type="string">Paint Fill</colorName><x type="number">-468</x><y type="number">-264</y><flipx type="string">-1</flipx><flipy type="string">1</flipy><rotation type="number">0</rotation><height type="number">53</height><ratio type="number">0.05798687089715536</ratio><itemID type="number">8</itemID></item><item id="10"><productid type="number">60</productid><name type="string">Motif (Laser)</name><type type="string">Motif</type><part type="string">Headstone</part><side type="string">Front</side><src type="string">1_037_10</src><item type="string">1_037_10</item><price type="number">40</price><quantity type="number">1</quantity><color type="string">#ffffff</color><colorName type="string">Paint Fill</colorName><x type="number">457.33333333333337</x><y type="number">255</y><flipx type="string">1</flipx><flipy type="string">-1</flipy><rotation type="number">0</rotation><height type="number">53</height><ratio type="number">0.05798687089715536</ratio><itemID type="number">9</itemID></item><item id="11"><productid type="number">21</productid><id type="number">21</id><uid type="number">1656830251943</uid><path type="string">../upload/2022/07/</path><name type="string">Laser-etched Image</name><type type="string">Photo</type><item type="string">1656830251943c71fe86fa3284a99a4ce7dd5.jpg</item><color type="number">1</color><mask type="number">0</mask><x type="number">297</x><y type="number">-39</y><flipx type="number">1</flipx><flipy type="number">1</flipy><rotation type="number">0</rotation><ratio type="number">1.9289870689655175</ratio><shape_url type="string">shapes/photos/oval_vertical.svg</shape_url><part type="string">Headstone</part><side type="string">Front</side><src type="string">C71FE86F-A328-4A99-A4CE-7DD57432C49D.jpeg</src><price type="number">0</price><quantity type="number">1</quantity><size type="number">153</size><width type="string">392</width><height type="string">559</height><itemID type="number">11</itemID></item></dyo>