<dyo id="1"><item id="2"><productid type="number">30</productid><type type="string">Headstone</type><shape type="string">Rectangle (Landscape)</shape><color type="string">#000000</color><fixed type="number">0</fixed><texture type="string">src/granites/forever2/l/18.jpg</texture><name type="string">Laser Etched Black Granite Plaque</name><price type="number">534.03</price><quantity type="number">1</quantity><width type="number">300</width><height type="number">200</height><_length type="number">1</_length><init_width type="number">1289</init_width><init_height type="number">873</init_height><device type="string">desktop</device><dpr type="number">1</dpr><orientation type="string">landscape</orientation><version type="string">1.43</version><version_date type="number">20220831</version_date><mode type="string">2d</mode><navigator type="string">Win32, Google Inc., Mozilla/5.0 (Windows NT 10.0; Win64; x64) AppleWebKit/537.36 (KHTML, like Gecko) Chrome/104.0.0.0 Safari/537.36, 1920x1080</navigator></item><item id="3"><productid type="string">16</productid><name type="string">Black Granite Inscription (free)</name><type type="string">Inscription</type><part type="string">Headstone</part><side type="string">Front</side><price type="number">0</price><quantity type="number">4</quantity><label type="string">test</label><font type="string">56.74499999999999px Garamond</font><font_size type="number">20</font_size><font_family type="string">Garamond</font_family><color type="string">#ffffff</color><colorName type="string">Paint Fill</colorName><x type="number">-353</x><y type="number">-245</y><rotation type="number">0</rotation><flipx type="number">1</flipx><flipy type="number">1</flipy><height type="number">10</height><itemID type="number">2</itemID></item><item id="4"><productid type="string">16</productid><name type="string">Black Granite Inscription (free)</name><type type="string">Inscription</type><part type="string">Headstone</part><side type="string">Front</side><price type="number">0</price><quantity type="number">4</quantity><label type="string">test</label><font type="string">56.74499999999999px Garamond</font><font_size type="number">20</font_size><font_family type="string">Garamond</font_family><color type="string">#ffffff</color><colorName type="string">Paint Fill</colorName><x type="number">-353</x><y type="number">-216</y><rotation type="number">0</rotation><flipx type="number">1</flipx><flipy type="number">1</flipy><height type="number">10</height><itemID type="number">3</itemID></item><item id="5"><productid type="string">16</productid><name type="string">Black Granite Inscription (free)</name><type type="string">Inscription</type><part type="string">Headstone</part><side type="string">Front</side><price type="number">0</price><quantity type="number">4</quantity><label type="string">test</label><font type="string">56.74499999999999px Garamond</font><font_size type="number">20</font_size><font_family type="string">Garamond</font_family><color type="string">#ffffff</color><colorName type="string">Paint Fill</colorName><x type="number">369</x><y type="number">-247</y><rotation type="number">0</rotation><flipx type="number">1</flipx><flipy type="number">1</flipy><height type="number">10</height><itemID type="number">4</itemID></item><item id="6"><productid type="string">16</productid><name type="string">Black Granite Inscription (free)</name><type type="string">Inscription</type><part type="string">Headstone</part><side type="string">Front</side><price type="number">0</price><quantity type="number">4</quantity><label type="string">test</label><font type="string">56.74499999999999px Garamond</font><font_size type="number">20</font_size><font_family type="string">Garamond</font_family><color type="string">#ffffff</color><colorName type="string">Paint Fill</colorName><x type="number">369</x><y type="number">-218</y><rotation type="number">0</rotation><flipx type="number">1</flipx><flipy type="number">1</flipy><height type="number">10</height><itemID type="number">5</itemID></item><item id="7"><productid type="string">16</productid><name type="string">Black Granite Inscription (free)</name><type type="string">Inscription</type><part type="string">Headstone</part><side type="string">Front</side><price type="number">0</price><quantity type="number">4</quantity><label type="string">test</label><font type="string">56.74499999999999px Garamond</font><font_size type="number">20</font_size><font_family type="string">Garamond</font_family><color type="string">#ffffff</color><colorName type="string">Paint Fill</colorName><x type="number">-355</x><y type="number">209</y><rotation type="number">0</rotation><flipx type="number">1</flipx><flipy type="number">1</flipy><height type="number">10</height><itemID type="number">6</itemID></item><item id="8"><productid type="string">16</productid><name type="string">Black Granite Inscription (free)</name><type type="string">Inscription</type><part type="string">Headstone</part><side type="string">Front</side><price type="number">0</price><quantity type="number">4</quantity><label type="string">test</label><font type="string">56.74499999999999px Garamond</font><font_size type="number">20</font_size><font_family type="string">Garamond</font_family><color type="string">#ffffff</color><colorName type="string">Paint Fill</colorName><x type="number">-355</x><y type="number">238</y><rotation type="number">0</rotation><flipx type="number">1</flipx><flipy type="number">1</flipy><height type="number">10</height><itemID type="number">7</itemID></item><item id="9"><productid type="string">16</productid><name type="string">Black Granite Inscription (free)</name><type type="string">Inscription</type><part type="string">Headstone</part><side type="string">Front</side><price type="number">0</price><quantity type="number">4</quantity><label type="string">test</label><font type="string">56.74499999999999px Garamond</font><font_size type="number">20</font_size><font_family type="string">Garamond</font_family><color type="string">#ffffff</color><colorName type="string">Paint Fill</colorName><x type="number">355</x><y type="number">203</y><rotation type="number">0</rotation><flipx type="number">1</flipx><flipy type="number">1</flipy><height type="number">10</height><itemID type="number">8</itemID></item><item id="10"><productid type="string">16</productid><name type="string">Black Granite Inscription (free)</name><type type="string">Inscription</type><part type="string">Headstone</part><side type="string">Front</side><price type="number">0</price><quantity type="number">4</quantity><label type="string">test</label><font type="string">56.74499999999999px Garamond</font><font_size type="number">20</font_size><font_family type="string">Garamond</font_family><color type="string">#ffffff</color><colorName type="string">Paint Fill</colorName><x type="number">355</x><y type="number">232</y><rotation type="number">0</rotation><flipx type="number">1</flipx><flipy type="number">1</flipy><height type="number">10</height><itemID type="number">9</itemID></item><item id="11"><productid type="string">71</productid><name type="string">Black Granite Motif (free)</name><type type="string">Motif</type><part type="string">Headstone</part><side type="string">Front</side><src type="string">2_057_23</src><item type="string">2_057_23</item><price type="number">0</price><quantity type="number">1</quantity><color type="string">#ffffff</color><colorName type="string">Paint Fill</colorName><x type="number">-316</x><y type="number">-10</y><flipx type="number">1</flipx><flipy type="number">1</flipy><rotation type="number">0</rotation><height type="number">40</height><ratio type="number">0.07590132827324478</ratio><itemID type="number">10</itemID></item><item id="12"><productid type="string">71</productid><name type="string">Black Granite Motif (free)</name><type type="string">Motif</type><part type="string">Headstone</part><side type="string">Front</side><src type="string">2_057_12</src><item type="string">2_057_12</item><price type="number">0</price><quantity type="number">1</quantity><color type="string">#ffffff</color><colorName type="string">Paint Fill</colorName><x type="number">327</x><y type="number">-6</y><flipx type="number">-1</flipx><flipy type="number">1</flipy><rotation type="number">0</rotation><height type="number">40</height><ratio type="number">0.0676818950930626</ratio><itemID type="number">11</itemID></item><item id="13"><productid type="string">71</productid><name type="string">Black Granite Motif (free)</name><type type="string">Motif</type><part type="string">Headstone</part><side type="string">Front</side><src type="string">1_137_09</src><item type="string">1_137_09</item><price type="number">0</price><quantity type="number">1</quantity><color type="string">#ffffff</color><colorName type="string">Paint Fill</colorName><x type="number">0</x><y type="number">-198</y><flipx type="number">1</flipx><flipy type="number">1</flipy><rotation type="number">0</rotation><height type="number">40</height><ratio type="number">0.10840108401084012</ratio><itemID type="number">12</itemID></item><item id="14"><productid type="string">71</productid><name type="string">Black Granite Motif (free)</name><type type="string">Motif</type><part type="string">Headstone</part><side type="string">Front</side><src type="string">2_031_04</src><item type="string">2_031_04</item><price type="number">0</price><quantity type="number">1</quantity><color type="string">#ffffff</color><colorName type="string">Paint Fill</colorName><x type="number">-4</x><y type="number">202</y><flipx type="number">1</flipx><flipy type="number">1</flipy><rotation type="number">0</rotation><height type="number">40</height><ratio type="number">0.10723860589812333</ratio><itemID type="number">13</itemID></item></dyo>