<dyo id="1"><item id="2"><productid type="number">32</productid><type type="string">Headstone</type><border type="string">No Border</border><shape_url type="string">shapes/photos/noborder.svg</shape_url><shape type="string">Full-colour Plaque</shape><color type="string">../upload/2024/12/1735433079204img_0701_cropped.jpg</color><fixed type="number">0</fixed><texture type="string">src/ceramic/l/01.jpg</texture><name type="string">Full-colour Plaque</name><price type="number">600</price><quantity type="number">1</quantity><width type="number">250</width><height type="number">200</height><_length type="number">10</_length><init_width type="number">390</init_width><init_height type="number">607</init_height><backgroundOption type="string">photo</backgroundOption><device type="string">mobile</device><dpr type="number">3</dpr><orientation type="string">portrait</orientation><version type="string">1.45</version><version_date type="number">20241120</version_date><mode type="string">2d</mode><navigator type="string">Safari (mobile(ios)), 390x844</navigator></item><item id="3"><productid type="string">137</productid><id type="string">137</id><uid type="number">1735433255064</uid><path type="string">../upload/2024/12/</path><name type="string">Image (free)</name><type type="string">Photo</type><item type="string">1735433255064img_0704_cropped.jpg</item><color type="number">0</color><mask type="number">0</mask><x type="number">417</x><y type="number">-234.16527545909844</y><flipx type="number">1</flipx><flipy type="number">1</flipy><rotation type="number">0</rotation><ratio type="number">1.4559572368421052</ratio><shape_url type="string">shapes/photos/oval_vertical.svg</shape_url><part type="string">Headstone</part><side type="string">Front</side><src type="string">IMG_0704.jpeg</src><price type="number">0</price><quantity type="number">1</quantity><size type="number">97</size><width type="string">310</width><height type="string">443</height><itemID type="number">3</itemID></item><item id="4"><productid type="string">1701</productid><name type="string">Inscription (free)</name><type type="string">Inscription</type><part type="string">Headstone</part><side type="string">Front</side><price type="number">0</price><quantity type="number">16</quantity><label type="string">In Loving Memory Of</label><font type="string">91.25999999999999px Garamond</font><font_size type="number">20</font_size><font_family type="string">Garamond</font_family><color type="string">#ffffff</color><colorName type="string">White</colorName><x type="number">-141</x><y type="number">-312.3605173898623</y><rotation type="number">0</rotation><flipx type="number">1</flipx><flipy type="number">1</flipy><height type="number">20</height><itemID type="number">1</itemID></item><item id="5"><productid type="string">1701</productid><name type="string">Inscription (free)</name><type type="string">Inscription</type><part type="string">Headstone</part><side type="string">Front</side><price type="number">0</price><quantity type="number">21</quantity><label type="string">Lyle Vincent Clive James</label><font type="string">82.134px Garamond</font><font_size type="number">18</font_size><font_family type="string">Garamond</font_family><color type="string">#ffffff</color><colorName type="string">White</colorName><x type="number">-156</x><y type="number">-210.01160253176548</y><rotation type="number">0</rotation><flipx type="number">1</flipx><flipy type="number">1</flipy><height type="number">18</height><itemID type="number">2</itemID></item><item id="6"><productid type="string">1701</productid><name type="string">Inscription (free)</name><type type="string">Inscription</type><part type="string">Headstone</part><side type="string">Front</side><price type="number">0</price><quantity type="number">15</quantity><label type="string">Born 25th May 1983</label><font type="string">63.882px Lucida Calligraphy</font><font_size type="number">14</font_size><font_family type="string">Lucida Calligraphy</font_family><color type="string">#ffffff</color><colorName type="string">White</colorName><x type="number">-171</x><y type="number">-24.527462298042565</y><rotation type="number">0</rotation><flipx type="number">1</flipx><flipy type="number">1</flipy><height type="number">17</height><itemID type="number">4</itemID></item><item id="7"><productid type="string">1701</productid><name type="string">Inscription (free)</name><type type="string">Inscription</type><part type="string">Headstone</part><side type="string">Front</side><price type="number">0</price><quantity type="number">21</quantity><label type="string">Death 13th November 2023</label><font type="string">63.882px Lucida Calligraphy</font><font_size type="number">14</font_size><font_family type="string">Lucida Calligraphy</font_family><color type="string">#ffffff</color><colorName type="string">White</colorName><x type="number">-108</x><y type="number">81.47420715103931</y><rotation type="number">0</rotation><flipx type="number">1</flipx><flipy type="number">1</flipy><height type="number">14</height><itemID type="number">5</itemID></item></dyo>