<dyo id="1"><item id="2"><productid type="number">5</productid><type type="string">Headstone</type><border type="string">Border 6</border><shape_url type="string">shapes/photos/border6.svg</shape_url><fixingSystem type="number">2</fixingSystem><shape type="string">Rectangle (Landscape)</shape><color type="string">#4c0f1e</color><fixed type="number">0</fixed><texture type="string">src/bronzes/phoenix/l/09.jpg</texture><name type="string">Bronze Plaque - Maroon - Lugs with Studs</name><price type="number">456.39</price><quantity type="number">1</quantity><width type="number">158.75</width><height type="number">107.94999999999999</height><_length type="number">1</_length><init_width type="number">1188</init_width><init_height type="number">757</init_height><device type="string">desktop</device><dpr type="number">1.5</dpr><orientation type="string">landscape</orientation><version type="string">1.43</version><version_date type="number">20220928</version_date><mode type="string">2d</mode><navigator type="string">Win32, Google Inc., Mozilla/5.0 (Windows NT 10.0; WOW64) AppleWebKit/537.36 (KHTML, like Gecko) Chrome/105.0.0.0 Safari/537.36, 2294x960</navigator></item><item id="3"><productid type="string">78</productid><name type="string">Inscription (Bronze)</name><type type="string">Inscription</type><part type="string">Headstone</part><side type="string">Front</side><price type="number">0</price><quantity type="number">14</quantity><label type="string">In Loving Memory</label><font type="string">97.63511811023622px Franklin Gothic</font><font_size type="number">14</font_size><font_family type="string">Franklin Gothic</font_family><color type="string">#ffb35a</color><colorName type="string">Paint Fill</colorName><x type="number">1.4993581514762582</x><y type="number">-254.88771466314404</y><rotation type="number">0</rotation><flipx type="number">1</flipx><flipy type="number">1</flipy><height type="number">12</height><itemID type="number">2</itemID></item><item id="4"><productid type="string">78</productid><name type="string">Inscription (Bronze)</name><type type="string">Inscription</type><part type="string">Headstone</part><side type="string">Front</side><price type="number">0</price><quantity type="number">14</quantity><label type="string">James Reese Cole</label><font type="string">118.55692913385826px Franklin Gothic</font><font_size type="number">17</font_size><font_family type="string">Franklin Gothic</font_family><color type="string">#ffb35a</color><colorName type="string">Paint Fill</colorName><x type="number">-1.4993581514762582</x><y type="number">-146.883751651255</y><rotation type="number">0</rotation><flipx type="number">1</flipx><flipy type="number">1</flipy><height type="number">12</height><itemID type="number">4</itemID></item><item id="5"><productid type="string">78</productid><name type="string">Inscription (Bronze)</name><type type="string">Inscription</type><part type="string">Headstone</part><side type="string">Front</side><price type="number">0</price><quantity type="number">21</quantity><label type="string">Husband, Father, Friend</label><font type="string">76.71330708661417px Franklin Gothic</font><font_size type="number">11</font_size><font_family type="string">Franklin Gothic</font_family><color type="string">#ffb35a</color><colorName type="string">Paint Fill</colorName><x type="number">44.98074454428752</x><y type="number">-29.393659180977465</y><rotation type="number">0</rotation><flipx type="number">1</flipx><flipy type="number">1</flipy><height type="number">9</height><itemID type="number">7</itemID></item></dyo>