[{"productid":52,"type":"Headstone","corner":2,"hole":3,"shape":"Rectangle (Landscape)","color":"#000000","fixed":0,"texture":"src/metals/forever/l/brushed-ss-swatch.jpg","name":"Single Thickness Stainless Steel Plaque - Straight (No drilled holes)","price":242.26,"quantity":1,"width":180,"height":130,"_length":2,"init_width":1079,"init_height":845,"device":"desktop","dpr":2,"orientation":"landscape","version":"1.45","version_date":20250716,"mode":"2d","navigator":"Chrome (desktop), 2048x1152"},{"productid":"77","name":"Inscription (free)","type":"Inscription","part":"Headstone","side":"Front","price":0,"quantity":14,"label":"In loving memory","font":"54.925px Lucida Calligraphy","font_size":6,"font_family":"Lucida Calligraphy","color":"#000000","colorName":"Black","x":-16,"y":-438,"rotation":0,"flipx":1,"flipy":1,"height":7,"itemID":1},{"productid":"77","name":"Inscription (free)","type":"Inscription","part":"Headstone","side":"Front","price":0,"quantity":20,"label":"Dr William (Bill) Woods","font":"137.3125px Arial","font_size":15,"font_family":"Arial","color":"#000000","colorName":"Black","x":-22,"y":-311.1579284667969,"rotation":0,"flipx":1,"flipy":1,"height":14,"itemID":2},{"productid":"77","name":"Inscription (free)","type":"Inscription","part":"Headstone","side":"Front","price":0,"quantity":21,"label":"02/10/1921 - 04/03/2025","font":"54.925px Lucida Calligraphy","font_size":6,"font_family":"Lucida Calligraphy","color":"#000000","colorName":"Black","x":0,"y":-128.29571533203125,"rotation":0,"flipx":1,"flipy":1,"height":6,"itemID":3},{"productid":"77","name":"Inscription (free)","type":"Inscription","part":"Headstone","side":"Front","price":0,"quantity":32,"label":"Founding member of Langlauf Ski Lodge","font":"54.925px Lucida Calligraphy","font_size":6,"font_family":"Lucida Calligraphy","color":"#000000","colorName":"Black","x":4,"y":8.624282836914062,"rotation":0,"flipx":1,"flipy":1,"height":7,"itemID":4},{"productid":"77","name":"Inscription (free)","type":"Inscription","part":"Headstone","side":"Front","price":0,"quantity":35,"label":"Now playing the piano with a cat on his lap.","font":"64.07916666666667px Lucida Calligraphy","font_size":7,"font_family":"Lucida Calligraphy","color":"#000000","colorName":"Black","x":-4,"y":211.4663543701172,"rotation":0,"flipx":1,"flipy":1,"height":8,"itemID":5},{"productid":"75","name":"YAG Lasered Motif (Stainless Steel)","type":"Motif","part":"Headstone","side":"Front","src":"1_131_25","item":"1_131_25","price":0,"quantity":1,"color":"#000000","colorName":"Black","x":-698,"y":468,"flipx":1,"flipy":1,"rotation":0,"height":22,"ratio":0.028460543337645538,"itemID":6},{"productid":"75","name":"YAG Lasered Motif (Stainless Steel)","type":"Motif","part":"Headstone","side":"Front","src":"1_171_18","item":"1_171_18","price":9.42981,"quantity":1,"color":"#000000","colorName":"Black","x":660,"y":460,"flipx":1,"flipy":1,"rotation":0,"height":21,"ratio":0.03832116788321168,"itemID":8}]