[{"productid":5,"type":"Headstone","border":"Border 3","shape_url":"shapes/photos/border3.svg","fixingSystem":2,"corner":2,"hole":3,"shape":"Bronze Plaque","color":"#24160b","fixed":0,"texture":"src/bronzes/phoenix/l/04.jpg","name":"Bronze Plaque - Dark Brown - Lugs with Studs","price":922.3,"quantity":1,"width":304.79999999999995,"height":203.2,"_length":0,"init_width":1680,"init_height":881,"device":"desktop","dpr":1,"orientation":"landscape","version":"1.45","version_date":20240731,"mode":"2d","navigator":"Chrome (desktop), 1920x1080"},{"productid":"78","name":"Inscription (Bronze)","type":"Inscription","part":"Headstone","side":"Front","price":0,"quantity":19,"label":"xfjdkdkdkdkkdkkkkkk","font":"56.36318897637796px Garamond","font_size":20,"font_family":"Garamond","color":"#ffb35a","colorName":"Texas Rose","x":112,"y":195,"rotation":0,"flipx":1,"flipy":1,"height":20,"itemID":1},{"productid":"200","id":"200","name":"Bronze Emblem","type":"Emblem","item":"br146-mormon","color":"#ffb35a","x":-289,"y":18,"flipx":1,"flipy":1,"rotation":0,"ratio":0.9738945578231293,"part":"Headstone","side":"Front","src":"br146-mormon","price":99,"quantity":1,"size":"152.39999999999998 x 152.39999999999998 mm","itemID":2},{"productid":"51","name":"Motif (Bronze)","type":"Motif","part":"Headstone","side":"Front","src":"1_129_22","item":"1_129_22","price":0,"quantity":1,"color":"#ffb35a","colorName":"Texas Rose","x":85,"y":-6,"flipx":1,"flipy":1,"rotation":0,"height":45,"ratio":0.10843373493975904,"itemID":3}]