[{"productid":5,"type":"Headstone","border":"No Border","shape_url":"shapes/photos/noborder.svg","fixingSystem":2,"corner":2,"hole":3,"shape":"Bronze Plaque","color":"#24160b","fixed":0,"texture":"src/bronzes/phoenix/l/04.jpg","name":"Bronze Plaque - Dark Brown - Lugs with Studs","price":1774.01,"quantity":1,"width":406.4,"height":400,"_length":0,"init_width":1680,"init_height":847,"device":"desktop","dpr":1,"orientation":"landscape","version":"1.45","version_date":20250313,"mode":"2d","navigator":"Chrome (desktop), 1920x1080"},{"productid":"78","name":"Inscription (Bronze)","type":"Inscription","part":"Headstone","side":"Front","price":0,"quantity":22,"label":"The Navigator of Memories","font":"28.44869586614173px Arial","font_size":14,"font_family":"Arial","color":"#ffb35a","colorName":"Texas Rose","x":4,"y":-241,"rotation":0,"flipx":1,"flipy":1,"height":13,"itemID":10},{"productid":"78","name":"Inscription (Bronze)","type":"Inscription","part":"Headstone","side":"Front","price":0,"quantity":23,"label":"Te Whakatere o Te Maumahara","font":"36.57689468503936px Arial","font_size":18,"font_family":"Arial","color":"#ffb35a","colorName":"Texas Rose","x":11,"y":-280,"rotation":0,"flipx":1,"flipy":1,"height":13,"itemID":15},{"productid":"78","name":"Inscription (Bronze)","type":"Inscription","part":"Headstone","side":"Front","price":0,"quantity":43,"label":"E tū ki te kei o te waka, kia pakia koe e ngā ngaru o te wā","font":"18.28844734251968px Arial","font_size":9,"font_family":"Arial","color":"#ffb35a","colorName":"Texas Rose","x":12,"y":-84,"rotation":0,"flipx":1,"flipy":1,"height":8,"itemID":22},{"productid":"78","name":"Inscription (Bronze)","type":"Inscription","part":"Headstone","side":"Front","price":0,"quantity":67,"label":"Stand at the stern of the canoe and feel the spray of the future biting at your face","font":"18.28844734251968px Arial","font_size":9,"font_family":"Arial","color":"#ffb35a","colorName":"Texas Rose","x":18,"y":-62,"rotation":0,"flipx":1,"flipy":1,"height":8,"itemID":23},{"productid":"78","name":"Inscription (Bronze)","type":"Inscription","part":"Headstone","side":"Front","price":0,"quantity":72,"label":"This sculpture holds two time capsules containing memorial content from the Tāngata","font":"18.28844734251968px Arial","font_size":9,"font_family":"Arial","color":"#ffb35a","colorName":"Texas Rose","x":5,"y":-197,"rotation":0,"flipx":1,"flipy":1,"height":8,"itemID":21},{"productid":"78","name":"Inscription (Bronze)","type":"Inscription","part":"Headstone","side":"Front","price":0,"quantity":70,"label":"whenua Liaison Group - a collective comprised of Maniapoto ki te Raki, Raukawa, and","font":"18.28844734251968px Arial","font_size":9,"font_family":"Arial","color":"#ffb35a","colorName":"Texas Rose","x":14,"y":-176,"rotation":0,"flipx":1,"flipy":1,"height":8,"itemID":16},{"productid":"78","name":"Inscription (Bronze)","type":"Inscription","part":"Headstone","side":"Front","price":0,"quantity":64,"label":"Te Rōpu Kaumātua o Waikeria.  . It is fashioned in the shape of a Hoe Whakatere -","font":"18.28844734251968px Arial","font_size":9,"font_family":"Arial","color":"#ffb35a","colorName":"Texas Rose","x":14,"y":-159,"rotation":0,"flipx":1,"flipy":1,"height":8,"itemID":24},{"productid":"78","name":"Inscription (Bronze)","type":"Inscription","part":"Headstone","side":"Front","price":0,"quantity":64,"label":"a steering paddle, and symbolizes the journey and navigation through life.","font":"18.28844734251968px Arial","font_size":9,"font_family":"Arial","color":"#ffb35a","colorName":"Texas Rose","x":13,"y":-140,"rotation":0,"flipx":1,"flipy":1,"height":8,"itemID":17}]