[{"productid":124,"type":"Headstone","shape":"Serpentine","color":"#000000","fixed":0,"texture":"src/granites/forever2/l/Noble-Black.jpg","name":"Traditional Engraved Headstone","price":2158.81,"quantity":1,"width":825.5,"height":654.05,"_length":80,"init_width":786,"init_height":413,"device":"desktop","dpr":1.25,"orientation":"landscape","version":"1.44","version_date":20230714,"mode":"2d","navigator":"Chrome (desktop), 1536x864"},{"productid":124,"type":"Base","name":"Rectangle","shape":"Square","color":"#000000","fixed":0,"texture":"src/granites/forever2/l/African-Black.jpg","price":664,"quantity":1,"width":862,"height":101.6,"_length":250,"init_width":786,"init_height":413,"mode":"2d"},{"productid":126,"name":"Motif (Traditional Engraved)","type":"Motif","part":"Headstone","side":"Front","src":"1_009_26","item":"1_009_26","price":239.2587,"quantity":1,"color":"#c99d44","colorName":"Gold Gilding","x":-1.2688172043010753,"y":-138.30107526881721,"flipx":"1","flipy":"1","rotation":0,"height":100,"ratio":0.23094688221709006,"itemID":1},{"productid":126,"name":"Motif (Traditional Engraved)","type":"Motif","part":"Headstone","side":"Front","src":"2_131_22","item":"2_131_22","price":276.63854,"quantity":1,"color":"#c99d44","colorName":"Gold Gilding","x":-156.54032258064515,"y":46.627570487091845,"flipx":"1","flipy":"1","rotation":0,"height":252,"ratio":0.2736156351791531,"itemID":3},{"productid":126,"name":"Motif (Traditional Engraved)","type":"Motif","part":"Headstone","side":"Front","src":"2_152_23","item":"2_152_23","price":231.63518,"quantity":1,"color":"#c99d44","colorName":"Gold Gilding","x":319.9005376344086,"y":-95.06481343838261,"flipx":"1","flipy":"1","rotation":0,"height":69,"ratio":0.09362279511533243,"itemID":5},{"productid":126,"name":"Motif (Traditional Engraved)","type":"Motif","part":"Headstone","side":"Front","src":"2_117_17","item":"2_117_17","price":255.48942,"quantity":1,"color":"#c99d44","colorName":"Gold Gilding","x":189.68817204301075,"y":12.053763440860214,"flipx":"1","flipy":"1","rotation":0,"height":166,"ratio":0.2315202231520223,"itemID":7},{"productid":"126","name":"Motif (Traditional Engraved)","type":"Motif","part":"Headstone","side":"Front","src":"2_119_24","item":"2_119_24","price":232.12702000000002,"quantity":1,"color":"#c99d44","colorName":"Gold Gilding","x":15.061553490017223,"y":14.266239644727651,"flipx":1,"flipy":1,"rotation":0,"height":71,"ratio":0.09428950863213811,"itemID":14},{"productid":"125","name":"Inscription (Traditional Engraved)","type":"Inscription","part":"Headstone","side":"Front","price":18.7,"quantity":11,"label":"IANNUZZELLI","font":"60.88265288746345px Garamond","font_size":113,"font_family":"Garamond","color":"#c99d44","colorName":"Gold Gilding","x":0,"y":-73.59139784946237,"rotation":0,"flipx":1,"flipy":1,"height":80,"itemID":2},{"productid":"125","name":"Inscription (Traditional Engraved)","type":"Inscription","part":"Headstone","side":"Front","price":7.4,"quantity":6,"label":"JOSEPH","font":"26.93922694135551px Garamond","font_size":50,"font_family":"Garamond","color":"#c99d44","colorName":"Gold Gilding","x":-71.05376344086021,"y":39.96774193548387,"rotation":0,"flipx":1,"flipy":1,"height":43,"itemID":4},{"productid":"125","name":"Inscription (Traditional Engraved)","type":"Inscription","part":"Headstone","side":"Front","price":4.1,"quantity":5,"label":"IRENE","font":"26.93922694135551px Garamond","font_size":50,"font_family":"Garamond","color":"#c99d44","colorName":"Gold Gilding","x":108.13073448087152,"y":41.7130964768842,"rotation":0,"flipx":1,"flipy":1,"height":32,"itemID":6},{"productid":"125","name":"Inscription (Traditional Engraved)","type":"Inscription","part":"Headstone","side":"Front","price":18.7,"quantity":16,"label":"Always and Forever","font":"36.637348640243495px Chopin Script","font_size":68,"font_family":"Chopin Script","color":"#c99d44","colorName":"Gold Gilding","x":13.840268645512083,"y":139.5698924731183,"rotation":0,"flipx":1,"flipy":1,"height":80,"itemID":8},{"productid":"125","name":"Inscription (Traditional Engraved)","type":"Inscription","part":"Headstone","side":"Front","price":7.4,"quantity":9,"label":"Feb 7, 2014","font":"26.93922694135551px Garamond","font_size":50,"font_family":"Garamond","color":"#c99d44","colorName":"Gold Gilding","x":-68.51612903225806,"y":101.50537634408602,"rotation":0,"flipx":1,"flipy":1,"height":43,"itemID":9},{"productid":"125","name":"Inscription (Traditional Engraved)","type":"Inscription","part":"Headstone","side":"Front","price":7.4,"quantity":9,"label":"Mar 2, 1925","font":"26.93922694135551px Garamond","font_size":50,"font_family":"Garamond","color":"#c99d44","colorName":"Gold Gilding","x":-67.88172043010752,"y":71.05376344086021,"rotation":0,"flipx":1,"flipy":1,"height":41,"itemID":10},{"productid":"125","name":"Inscription (Traditional Engraved)","type":"Inscription","part":"Headstone","side":"Front","price":7.4,"quantity":10,"label":"Feb 14, 1927","font":"26.93922694135551px Garamond","font_size":50,"font_family":"Garamond","color":"#c99d44","colorName":"Gold Gilding","x":112.11524167794573,"y":71.66874941951235,"rotation":0,"flipx":1,"flipy":1,"height":43,"itemID":11},{"productid":"125","name":"Inscription (Traditional Engraved)","type":"Inscription","part":"Headstone","side":"Front","price":7.4,"quantity":10,"label":"Aug 19, 2023","font":"26.93922694135551px Garamond","font_size":50,"font_family":"Garamond","color":"#c99d44","colorName":"Gold Gilding","x":113.40351231588,"y":100.23655913978493,"rotation":0,"flipx":1,"flipy":1,"height":50,"itemID":12},{"productid":"125","name":"Inscription (Traditional Engraved)","type":"Inscription","part":"Headstone","side":"Front","price":4.1,"quantity":4,"label":"19??","font":"26.400442402528398px Chopin Script","font_size":49,"font_family":"Chopin Script","color":"#c99d44","colorName":"Gold Gilding","x":15.92952706291409,"y":41.1318871127261,"rotation":0,"flipx":1,"flipy":1,"height":35,"itemID":13}]