{
    "domain": "www.forevershining.com.au",
    "preview": "saved-designs\/screenshots\/2020\/07\/1594679034663.jpg",
    "product_name": "Bronze Plaque - Dark Brown - Lugs with Studs",
    "design_stampid": "1594679034663",
    "design_price": 620.8999999999999772626324556767940521240234375,
    "design_productid": "5",
    "design_orientation": "undefined",
    "design_shape": "Square",
    "design_texture": "src\/bronzes\/phoenix\/l\/04.jpg",
    "design_width": "185",
    "design_height": "235",
    "design_name": "alan mason",
    "ml_language": "English",
    "ml_style": "Bronze",
    "ml_type": "Plaque",
    "ml_motif": "Butterflies",
    "ml_tags": "ALAN RONALD MASON 10\/01\/76 - 11\/05\/20 Loving Father of Cooper Loved Son of Ronald and Helena Brother of Brian Brother in Law of Belinda Uncle of Thomas and Olivia Forever Loved and Never Forgotten"
}