{
    "domain": "www.forevershining.com.au",
    "preview": "saved-designs\/screenshots\/2023\/12\/1702080430644.jpg",
    "product_name": "Bronze Plaque - Maroon - Lugs with Studs",
    "design_stampid": "1702080430644",
    "design_price": 829.01999999999998181010596454143524169921875,
    "design_productid": "5",
    "design_orientation": "landscape",
    "design_shape": "Rectangle (Landscape)",
    "design_texture": "src\/bronzes\/phoenix\/l\/09.jpg",
    "design_width": "300",
    "design_height": "160",
    "design_name": "Trent",
    "ml_language": "English",
    "ml_style": "Bronze",
    "ml_type": "Plaque",
    "ml_motif": "Australian Flora",
    "ml_tags": "1994 -2021 TRENT RILEY In Memory of TBUNS Local Skateboard Legend"
}