{
    "domain": "bronze-plaque.com",
    "preview": "saved-designs\/screenshots\/2023\/09\/1694519214787.jpg",
    "product_name": "Bronze Plaque - Brown - Lugs with Studs",
    "design_stampid": "1694519214787",
    "design_price": 443.259999999999990905052982270717620849609375,
    "design_productid": "5",
    "design_orientation": "landscape",
    "design_shape": "Rectangle (Landscape)",
    "design_texture": "src\/bronzes\/phoenix\/l\/02.jpg",
    "design_width": "152.39999999999998",
    "design_height": "101.6",
    "design_name": "Randy",
    "ml_language": "English",
    "ml_style": "Bronze",
    "ml_type": "Plaque",
    "ml_motif": "Religious",
    "ml_tags": "Randy Hough Happy trails Big O, thanks for memories. 1958 - 2023 Brother, Friend, Father."
}