<dyo id="1"><item id="2"><productid type="number">4</productid><type type="string">Headstone</type><shape type="string">Headstone 28</shape><color type="string">#000000</color><fixed type="number">4</fixed><texture type="string">src/granites/forever2/l/18.jpg</texture><name type="string">Laser Etched Black Granite Headstone</name><price type="number">1774.85</price><quantity type="number">1</quantity><width type="number">371</width><height type="number">609.5999999999999</height><_length type="number">80</_length><init_width type="number">1008</init_width><init_height type="number">661</init_height><device type="string">desktop</device><dpr type="number">1</dpr><orientation type="string">landscape</orientation><version type="string">1.44</version><version_date type="number">20230919</version_date><mode type="string">2d</mode><navigator type="string">Mozilla Firefox (desktop), 1440x900</navigator></item><item id="3"><productid type="number">21</productid><id type="number">21</id><uid type="number">1719287099261</uid><path type="string">../upload/2024/06/</path><name type="string">Laser-etched Image</name><type type="string">Photo</type><item type="string">1719287099261diana_age_14_cropped.jpg</item><color type="number">1</color><mask type="number">0</mask><x type="number">12.161026587548122</x><y type="number">-82.04975922953452</y><flipx type="number">1</flipx><flipy type="number">1</flipy><rotation type="number">0</rotation><ratio type="number">1.2605191929133859</ratio><shape_url type="string">shapes/photos/oval_vertical.svg</shape_url><part type="string">Headstone</part><side type="string">Front</side><src type="string">Diana age 14.jpg</src><price type="number">0</price><quantity type="number">1</quantity><size type="number">372</size><width type="string">265</width><height type="string">393</height><itemID type="number">1</itemID></item><item id="4"><productid type="string">16</productid><name type="string">Black Granite Inscription (free)</name><type type="string">Inscription</type><part type="string">Headstone</part><side type="string">Front</side><price type="number">0</price><quantity type="number">20</quantity><label type="string">Diana Rosalind Trimble</label><font type="string">34.887918307086615px Garamond</font><font_size type="number">33</font_size><font_family type="string">Garamond</font_family><color type="string">#ffffff</color><colorName type="string">White</colorName><x type="number">2.3887474373033486</x><y type="number">168</y><rotation type="number">0</rotation><flipx type="number">1</flipx><flipy type="number">1</flipy><height type="number">24</height><itemID type="number">2</itemID></item><item id="5"><productid type="string">16</productid><name type="string">Black Granite Inscription (free)</name><type type="string">Inscription</type><part type="string">Headstone</part><side type="string">Front</side><price type="number">0</price><quantity type="number">13</quantity><label type="string">Natural Wonder</label><font type="string">14.80093503937008px Garamond</font><font_size type="number">14</font_size><font_family type="string">Garamond</font_family><color type="string">#ffffff</color><colorName type="string">White</colorName><x type="number">-172.06912352827771</x><y type="number">-101</y><rotation type="number">0</rotation><flipx type="number">1</flipx><flipy type="number">1</flipy><height type="number">10</height><itemID type="number">3</itemID></item><item id="6"><productid type="string">16</productid><name type="string">Black Granite Inscription (free)</name><type type="string">Inscription</type><part type="string">Headstone</part><side type="string">Front</side><price type="number">0</price><quantity type="number">14</quantity><label type="string">Master Vocalist</label><font type="string">16.915354330708663px Garamond</font><font_size type="number">16</font_size><font_family type="string">Garamond</font_family><color type="string">#ffffff</color><colorName type="string">White</colorName><x type="number">-177.96417473717503</x><y type="number">-61</y><rotation type="number">0</rotation><flipx type="number">1</flipx><flipy type="number">1</flipy><height type="number">12</height><itemID type="number">5</itemID></item><item id="7"><productid type="string">16</productid><name type="string">Black Granite Inscription (free)</name><type type="string">Inscription</type><part type="string">Headstone</part><side type="string">Front</side><price type="number">0</price><quantity type="number">10</quantity><label type="string">Songwriter</label><font type="string">19.029773622047244px Garamond</font><font_size type="number">18</font_size><font_family type="string">Garamond</font_family><color type="string">#ffffff</color><colorName type="string">White</colorName><x type="number">-175.12833130098102</x><y type="number">-38</y><rotation type="number">0</rotation><flipx type="number">1</flipx><flipy type="number">1</flipy><height type="number">17</height><itemID type="number">7</itemID></item><item id="8"><productid type="string">16</productid><name type="string">Black Granite Inscription (free)</name><type type="string">Inscription</type><part type="string">Headstone</part><side type="string">Front</side><price type="number">0</price><quantity type="number">9</quantity><label type="string">Performer</label><font type="string">16.915354330708663px Garamond</font><font_size type="number">16</font_size><font_family type="string">Garamond</font_family><color type="string">#ffffff</color><colorName type="string">White</colorName><x type="number">-167.0370147119799</x><y type="number">10</y><rotation type="number">0</rotation><flipx type="number">1</flipx><flipy type="number">1</flipy><height type="number">12</height><itemID type="number">8</itemID></item><item id="9"><productid type="string">16</productid><name type="string">Black Granite Inscription (free)</name><type type="string">Inscription</type><part type="string">Headstone</part><side type="string">Front</side><price type="number">0</price><quantity type="number">10</quantity><label type="string">Truthsayer</label><font type="string">16.915354330708663px Garamond</font><font_size type="number">16</font_size><font_family type="string">Garamond</font_family><color type="string">#ffffff</color><colorName type="string">White</colorName><x type="number">183.17916530432217</x><y type="number">27</y><rotation type="number">0</rotation><flipx type="number">1</flipx><flipy type="number">1</flipy><height type="number">16</height><itemID type="number">9</itemID></item><item id="10"><productid type="string">16</productid><name type="string">Black Granite Inscription (free)</name><type type="string">Inscription</type><part type="string">Headstone</part><side type="string">Front</side><price type="number">0</price><quantity type="number">6</quantity><label type="string">Writer</label><font type="string">16.915354330708663px Garamond</font><font_size type="number">16</font_size><font_family type="string">Garamond</font_family><color type="string">#ffffff</color><colorName type="string">White</colorName><x type="number">182.0057533907152</x><y type="number">-111.97660115559904</y><rotation type="number">0</rotation><flipx type="number">1</flipx><flipy type="number">1</flipy><height type="number">11</height><itemID type="number">15</itemID></item><item id="11"><productid type="string">16</productid><name type="string">Black Granite Inscription (free)</name><type type="string">Inscription</type><part type="string">Headstone</part><side type="string">Front</side><price type="number">0</price><quantity type="number">11</quantity><label type="string">Inspiration</label><font type="string">15.858144685039372px Garamond</font><font_size type="number">15</font_size><font_family type="string">Garamond</font_family><color type="string">#ffffff</color><colorName type="string">White</colorName><x type="number">-120.03437734852821</x><y type="number">88.23619995117178</y><rotation type="number">0</rotation><flipx type="number">1</flipx><flipy type="number">1</flipy><height type="number">14</height><itemID type="number">19</itemID></item><item id="12"><productid type="string">16</productid><name type="string">Black Granite Inscription (free)</name><type type="string">Inscription</type><part type="string">Headstone</part><side type="string">Front</side><price type="number">0</price><quantity type="number">9</quantity><label type="string">Life force</label><font type="string">15.858144685039372px Garamond</font><font_size type="number">15</font_size><font_family type="string">Garamond</font_family><color type="string">#ffffff</color><colorName type="string">White</colorName><x type="number">154.03412782863427</x><y type="number">66.23619995117178</y><rotation type="number">0</rotation><flipx type="number">1</flipx><flipy type="number">1</flipy><height type="number">11</height><itemID type="number">21</itemID></item><item id="13"><productid type="string">16</productid><name type="string">Black Granite Inscription (free)</name><type type="string">Inscription</type><part type="string">Headstone</part><side type="string">Front</side><price type="number">0</price><quantity type="number">10</quantity><label type="string">Adventurer</label><font type="string">15.858144685039372px Garamond</font><font_size type="number">15</font_size><font_family type="string">Garamond</font_family><color type="string">#ffffff</color><colorName type="string">White</colorName><x type="number">-130.40908306258996</x><y type="number">74.23619995117178</y><rotation type="number">0</rotation><flipx type="number">1</flipx><flipy type="number">1</flipy><height type="number">11</height><itemID type="number">22</itemID></item><item id="14"><productid type="string">16</productid><name type="string">Black Granite Inscription (free)</name><type type="string">Inscription</type><part type="string">Headstone</part><side type="string">Front</side><price type="number">0</price><quantity type="number">9</quantity><label type="string">Humourist</label><font type="string">15.858144685039372px Garamond</font><font_size type="number">15</font_size><font_family type="string">Garamond</font_family><color type="string">#ffffff</color><colorName type="string">White</colorName><x type="number">193.26765585668682</x><y type="number">4.236199951171784</y><rotation type="number">0</rotation><flipx type="number">1</flipx><flipy type="number">1</flipy><height type="number">10</height><itemID type="number">23</itemID></item><item id="15"><productid type="string">16</productid><name type="string">Black Granite Inscription (free)</name><type type="string">Inscription</type><part type="string">Headstone</part><side type="string">Front</side><price type="number">0</price><quantity type="number">11</quantity><label type="string">Free Thinker</label><font type="string">15.858144685039372px Garamond</font><font_size type="number">15</font_size><font_family type="string">Garamond</font_family><color type="string">#ffffff</color><colorName type="string">White</colorName><x type="number">-143.234246861224</x><y type="number">56.236199951171784</y><rotation type="number">0</rotation><flipx type="number">1</flipx><flipy type="number">1</flipy><height type="number">11</height><itemID type="number">27</itemID></item><item id="16"><productid type="string">16</productid><name type="string">Black Granite Inscription (free)</name><type type="string">Inscription</type><part type="string">Headstone</part><side type="string">Front</side><price type="number">0</price><quantity type="number">4</quantity><label type="string">Poet</label><font type="string">17.972563976377955px Garamond</font><font_size type="number">17</font_size><font_family type="string">Garamond</font_family><color type="string">#ffffff</color><colorName type="string">White</colorName><x type="number">-88.41041509395069</x><y type="number">107.23619995117178</y><rotation type="number">0</rotation><flipx type="number">1</flipx><flipy type="number">1</flipy><height type="number">11</height><itemID type="number">29</itemID></item><item id="17"><productid type="string">16</productid><name type="string">Black Granite Inscription (free)</name><type type="string">Inscription</type><part type="string">Headstone</part><side type="string">Front</side><price type="number">0</price><quantity type="number">27</quantity><label type="string">30th June 1966 - 3rd January 2021</label><font type="string">19.029773622047244px Garamond</font><font_size type="number">18</font_size><font_family type="string">Garamond</font_family><color type="string">#ffffff</color><colorName type="string">White</colorName><x type="number">2.1829855537720846</x><y type="number">199.23619995117178</y><rotation type="number">0</rotation><flipx type="number">1</flipx><flipy type="number">1</flipy><height type="number">18</height><itemID type="number">30</itemID></item><item id="18"><productid type="string">16</productid><name type="string">Black Granite Inscription (free)</name><type type="string">Inscription</type><part type="string">Headstone</part><side type="string">Front</side><price type="number">0</price><quantity type="number">9</quantity><label type="string">Raconteur</label><font type="string">14.80093503937008px Garamond</font><font_size type="number">14</font_size><font_family type="string">Garamond</font_family><color type="string">#ffffff</color><colorName type="string">White</colorName><x type="number">172.9421120297634</x><y type="number">45.14079996744783</y><rotation type="number">0</rotation><flipx type="number">1</flipx><flipy type="number">1</flipy><height type="number">9</height><itemID type="number">32</itemID></item><item id="19"><productid type="string">16</productid><name type="string">Black Granite Inscription (free)</name><type type="string">Inscription</type><part type="string">Headstone</part><side type="string">Front</side><price type="number">0</price><quantity type="number">8</quantity><label type="string">Lyricist</label><font type="string">19.029773622047244px Garamond</font><font_size type="number">18</font_size><font_family type="string">Garamond</font_family><color type="string">#ffffff</color><colorName type="string">White</colorName><x type="number">-159.9788188978407</x><y type="number">-12.859200032552167</y><rotation type="number">0</rotation><flipx type="number">1</flipx><flipy type="number">1</flipy><height type="number">17</height><itemID type="number">34</itemID></item><item id="20"><productid type="string">16</productid><name type="string">Black Granite Inscription (free)</name><type type="string">Inscription</type><part type="string">Headstone</part><side type="string">Front</side><price type="number">0</price><quantity type="number">6</quantity><label type="string">Singer</label><font type="string">16.915354330708663px Garamond</font><font_size type="number">16</font_size><font_family type="string">Garamond</font_family><color type="string">#ffffff</color><colorName type="string">White</colorName><x type="number">-163.29867647096717</x><y type="number">-83.82000071207682</y><rotation type="number">0</rotation><flipx type="number">1</flipx><flipy type="number">1</flipy><height type="number">15</height><itemID type="number">35</itemID></item><item id="21"><productid type="string">16</productid><name type="string">Black Granite Inscription (free)</name><type type="string">Inscription</type><part type="string">Headstone</part><side type="string">Front</side><price type="number">0</price><quantity type="number">9</quantity><label type="string">Intellect</label><font type="string">16.915354330708663px Garamond</font><font_size type="number">16</font_size><font_family type="string">Garamond</font_family><color type="string">#ffffff</color><colorName type="string">White</colorName><x type="number">191.45064141045884</x><y type="number">-63.82000071207682</y><rotation type="number">0</rotation><flipx type="number">1</flipx><flipy type="number">1</flipy><height type="number">12</height><itemID type="number">36</itemID></item><item id="22"><productid type="string">16</productid><name type="string">Black Granite Inscription (free)</name><type type="string">Inscription</type><part type="string">Headstone</part><side type="string">Front</side><price type="number">0</price><quantity type="number">8</quantity><label type="string">Radiance</label><font type="string">15.858144685039372px Garamond</font><font_size type="number">15</font_size><font_family type="string">Garamond</font_family><color type="string">#ffffff</color><colorName type="string">White</colorName><x type="number">147.92133285582884</x><y type="number">85.17999928792318</y><rotation type="number">0</rotation><flipx type="number">1</flipx><flipy type="number">1</flipy><height type="number">11</height><itemID type="number">37</itemID></item><item id="23"><productid type="string">16</productid><name type="string">Black Granite Inscription (free)</name><type type="string">Inscription</type><part type="string">Headstone</part><side type="string">Front</side><price type="number">0</price><quantity type="number">8</quantity><label type="string">Kindness</label><font type="string">16.915354330708663px Garamond</font><font_size type="number">16</font_size><font_family type="string">Garamond</font_family><color type="string">#ffffff</color><colorName type="string">White</colorName><x type="number">197.58007260472675</x><y type="number">-19.065100097656227</y><rotation type="number">0</rotation><flipx type="number">1</flipx><flipy type="number">1</flipy><height type="number">12</height><itemID type="number">39</itemID></item><item id="24"><productid type="string">16</productid><name type="string">Black Granite Inscription (free)</name><type type="string">Inscription</type><part type="string">Headstone</part><side type="string">Front</side><price type="number">0</price><quantity type="number">15</quantity><label type="string">Recording Artist</label><font type="string">16.915354330708663px Garamond</font><font_size type="number">16</font_size><font_family type="string">Garamond</font_family><color type="string">#ffffff</color><colorName type="string">White</colorName><x type="number">-162.9195782845394</x><y type="number">33.93489990234377</y><rotation type="number">0</rotation><flipx type="number">1</flipx><flipy type="number">1</flipy><height type="number">16</height><itemID type="number">40</itemID></item><item id="25"><productid type="string">16</productid><name type="string">Black Granite Inscription (free)</name><type type="string">Inscription</type><part type="string">Headstone</part><side type="string">Front</side><price type="number">0</price><quantity type="number">6</quantity><label type="string">Beauty</label><font type="string">16.915354330708663px Garamond</font><font_size type="number">16</font_size><font_family type="string">Garamond</font_family><color type="string">#ffffff</color><colorName type="string">White</colorName><x type="number">130.4580255533598</x><y type="number">101.94156494140623</y><rotation type="number">0</rotation><flipx type="number">1</flipx><flipy type="number">1</flipy><height type="number">15</height><itemID type="number">43</itemID></item><item id="26"><productid type="string">16</productid><name type="string">Black Granite Inscription (free)</name><type type="string">Inscription</type><part type="string">Headstone</part><side type="string">Front</side><price type="number">0</price><quantity type="number">12</quantity><label type="string">Sez love is all</label><font type="string">16.915354330708663px Garamond</font><font_size type="number">16</font_size><font_family type="string">Garamond</font_family><color type="string">#ffffff</color><colorName type="string">White</colorName><x type="number">2.1219903691813897</x><y type="number">231.94156494140623</y><rotation type="number">0</rotation><flipx type="number">1</flipx><flipy type="number">1</flipy><height type="number">12</height><itemID type="number">44</itemID></item><item id="27"><productid type="string">16</productid><name type="string">Black Granite Inscription (free)</name><type type="string">Inscription</type><part type="string">Headstone</part><side type="string">Front</side><price type="number">0</price><quantity type="number">28</quantity><label type="string">Friend of the Sea, Trees &amp; the Wind</label><font type="string">12.686515748031496px Garamond</font><font_size type="number">12</font_size><font_family type="string">Garamond</font_family><color type="string">#ffffff</color><colorName type="string">White</colorName><x type="number">3.1829855537720704</x><y type="number">136.8770645141601</y><rotation type="number">0</rotation><flipx type="number">1</flipx><flipy type="number">1</flipy><height type="number">10</height><itemID type="number">45</itemID></item><item id="28"><productid type="string">16</productid><name type="string">Black Granite Inscription (free)</name><type type="string">Inscription</type><part type="string">Headstone</part><side type="string">Front</side><price type="number">0</price><quantity type="number">23</quantity><label type="string">Dancing in the Grassy Paths</label><font type="string">16.915354330708663px Garamond</font><font_size type="number">16</font_size><font_family type="string">Garamond</font_family><color type="string">#ffffff</color><colorName type="string">White</colorName><x type="number">-9.57193871109871</x><y type="number">310.2361999511718</y><rotation type="number">0</rotation><flipx type="number">1</flipx><flipy type="number">1</flipy><height type="number">16</height><itemID type="number">25</itemID></item><item id="29"><productid type="string">16</productid><name type="string">Black Granite Inscription (free)</name><type type="string">Inscription</type><part type="string">Headstone</part><side type="string">Front</side><price type="number">0</price><quantity type="number">8</quantity><label type="string">Activist</label><font type="string">16.915354330708663px Garamond</font><font_size type="number">16</font_size><font_family type="string">Garamond</font_family><color type="string">#ffffff</color><colorName type="string">White</colorName><x type="number">187.79661605118986</x><y type="number">-43.763800048828216</y><rotation type="number">0</rotation><flipx type="number">1</flipx><flipy type="number">1</flipy><height type="number">11</height><itemID type="number">18</itemID></item><item id="30"><productid type="string">16</productid><name type="string">Black Granite Inscription (free)</name><type type="string">Inscription</type><part type="string">Headstone</part><side type="string">Front</side><price type="number">0</price><quantity type="number">6</quantity><label type="string">Artist</label><font type="string">19.029773622047244px Garamond</font><font_size type="number">18</font_size><font_family type="string">Garamond</font_family><color type="string">#ffffff</color><colorName type="string">White</colorName><x type="number">190.08094989037158</x><y type="number">-87.06510009765623</y><rotation type="number">0</rotation><flipx type="number">1</flipx><flipy type="number">1</flipy><height type="number">13</height><itemID type="number">41</itemID></item><item id="31"><productid type="string">16</productid><name type="string">Black Granite Inscription (free)</name><type type="string">Inscription</type><part type="string">Headstone</part><side type="string">Front</side><price type="number">0</price><quantity type="number">12</quantity><label type="string">I&amp;apos;ll always BE</label><font type="string">16.915354330708663px Garamond</font><font_size type="number">16</font_size><font_family type="string">Garamond</font_family><color type="string">#ffffff</color><colorName type="string">White</colorName><x type="number">3.9521318942927337</x><y type="number">-301.0584350585938</y><rotation type="number">0</rotation><flipx type="number">1</flipx><flipy type="number">1</flipy><height type="number">16</height><itemID type="number">42</itemID></item><item id="32"><productid type="string">16</productid><name type="string">Black Granite Inscription (free)</name><type type="string">Inscription</type><part type="string">Headstone</part><side type="string">Front</side><price type="number">0</price><quantity type="number">29</quantity><label type="string">Loved Forever Daughter and Sister</label><font type="string">19.029773622047244px Garamond</font><font_size type="number">18</font_size><font_family type="string">Garamond</font_family><color type="string">#ffffff</color><colorName type="string">White</colorName><x type="number">-14.312760960185642</x><y type="number">288</y><rotation type="number">0</rotation><flipx type="number">1</flipx><flipy type="number">1</flipy><height type="number">18</height><itemID type="number">6</itemID></item></dyo>