<dyo id="1"><item id="2"><productid type="number">34</productid><type type="string">Headstone</type><corner type="number">2</corner><hole type="number">3</hole><shape type="string">Rectangle (Landscape)</shape><color type="string">#000000</color><fixed type="number">0</fixed><texture type="string">src/granites/forever2/l/G633.jpg</texture><name type="string">Traditional Engraved Plaque</name><price type="number">1278.02</price><quantity type="number">1</quantity><width type="string">914.4</width><height type="number">762</height><_length type="number">25.4</_length><init_width type="number">351</init_width><init_height type="number">584.0040664672852</init_height><device type="string">mobile</device><dpr type="number">3.075000047683716</dpr><orientation type="string">portrait</orientation><version type="string">1.45</version><version_date type="number">20250629</version_date><mode type="string">2d</mode><navigator type="string">Chrome (mobile(android)), 352x781</navigator></item><item id="3"><productid type="string">126</productid><name type="string">Motif (Traditional Engraved)</name><type type="string">Motif</type><part type="string">Headstone</part><side type="string">Front</side><src type="string">bronze8</src><item type="string">bronze8</item><price type="number">265.81806</price><quantity type="number">1</quantity><color type="string">#eeeeee</color><colorName type="string">Silver Gilding</colorName><colorName2 type="undefined">undefined</colorName2><x type="number">-368.2733524667014</x><y type="number">-297.74024810724393</y><flipx type="number">-1</flipx><flipy type="number">1</flipy><rotation type="number">0</rotation><height type="number">208</height><ratio type="number">0.26804123711340205</ratio><itemID type="number">7</itemID></item><item id="4"><productid type="string">126</productid><name type="string">Motif (Traditional Engraved)</name><type type="string">Motif</type><part type="string">Headstone</part><side type="string">Front</side><src type="string">bronze8</src><item type="string">bronze8</item><price type="number">265.81806</price><quantity type="number">1</quantity><color type="string">#eeeeee</color><colorName type="string">Silver Gilding</colorName><colorName2 type="undefined">undefined</colorName2><x type="number">509.44090025018886</x><y type="number">-301.7363711996734</y><flipx type="number">1</flipx><flipy type="number">-1</flipy><rotation type="number">0</rotation><height type="number">208</height><ratio type="number">0.26804123711340205</ratio><itemID type="number">8</itemID></item><item id="5"><productid type="string">125</productid><name type="string">Inscription (Traditional Engraved)</name><type type="string">Inscription</type><part type="string">Headstone</part><side type="string">Front</side><price type="number">16.5</price><quantity type="number">5</quantity><label type="string">BODEN</label><font type="string">115.08550867438316px Garamond</font><font_size type="number">100</font_size><font_family type="string">Garamond</font_family><color type="string">#ffffff</color><colorName type="string">White</colorName><x type="number">25.96801042374375</x><y type="number">-316.72382602717596</y><rotation type="number">0</rotation><flipx type="number">1</flipx><flipy type="number">1</flipy><height type="number">69</height><itemID type="number">1</itemID></item><item id="6"><productid type="string">125</productid><name type="string">Inscription (Traditional Engraved)</name><type type="string">Inscription</type><part type="string">Headstone</part><side type="string">Front</side><price type="number">16.5</price><quantity type="number">12</quantity><label type="string">"Len"                Saundra</label><font type="string">113.93465358763933px Garamond</font><font_size type="number">99</font_size><font_family type="string">Garamond</font_family><color type="string">#ffffff</color><colorName type="string">White</colorName><x type="number">158.80660494160998</x><y type="number">-115.82964332722077</y><rotation type="number">0</rotation><flipx type="number">1</flipx><flipy type="number">1</flipy><height type="number">72</height><itemID type="number">2</itemID></item><item id="7"><productid type="string">125</productid><name type="string">Inscription (Traditional Engraved)</name><type type="string">Inscription</type><part type="string">Headstone</part><side type="string">Front</side><price type="number">7.15</price><quantity type="number">19</quantity><label type="string">Leonard Norris                     Eileen</label><font type="string">85.16327641904354px Garamond</font><font_size type="number">74</font_size><font_family type="string">Garamond</font_family><color type="string">#ffffff</color><colorName type="string">White</colorName><x type="number">10.98601672191478</x><y type="number">21.127648400628573</y><rotation type="number">0</rotation><flipx type="number">1</flipx><flipy type="number">1</flipy><height type="number">54</height><itemID type="number">3</itemID></item><item id="8"><productid type="string">125</productid><name type="string">Inscription (Traditional Engraved)</name><type type="string">Inscription</type><part type="string">Headstone</part><side type="string">Front</side><price type="number">7.15</price><quantity type="number">19</quantity><label type="string">8-14-1934                                     08-09-1954</label><font type="string">73.65472555160522px Garamond</font><font_size type="number">64</font_size><font_family type="string">Garamond</font_family><color type="string">#ffffff</color><colorName type="string">White</colorName><x type="number">159.80532947022084</x><y type="number">169.06786905791841</y><rotation type="number">0</rotation><flipx type="number">1</flipx><flipy type="number">1</flipy><height type="number">45</height><itemID type="number">4</itemID></item><item id="9"><productid type="string">125</productid><name type="string">Inscription (Traditional Engraved)</name><type type="string">Inscription</type><part type="string">Headstone</part><side type="string">Front</side><price type="number">7.15</price><quantity type="number">17</quantity><label type="string">What is love?  Cor 1:9</label><font type="string">73.65472555160522px Garamond</font><font_size type="number">64</font_size><font_family type="string">Garamond</font_family><color type="string">#ffffff</color><colorName type="string">White</colorName><x type="number">110.86534148698343</x><y type="number">377.87096833697683</y><rotation type="number">0</rotation><flipx type="number">1</flipx><flipy type="number">1</flipy><height type="number">50</height><itemID type="number">5</itemID></item><item id="10"><productid type="string">125</productid><name type="string">Inscription (Traditional Engraved)</name><type type="string">Inscription</type><part type="string">Headstone</part><side type="string">Front</side><price type="number">7.15</price><quantity type="number">9</quantity><label type="string">8-26-2024</label><font type="string">71.35301537811756px Garamond</font><font_size type="number">62</font_size><font_family type="string">Garamond</font_family><color type="string">#ffffff</color><colorName type="string">White</colorName><x type="number">-284.6549017279063</x><y type="number">249.0456082581668</y><rotation type="number">0</rotation><flipx type="number">1</flipx><flipy type="number">1</flipy><height type="number">43</height><itemID type="number">9</itemID></item></dyo>