{
    "domain": "localhost",
    "preview": "saved-designs\/screenshots\/2024\/04\/1713512573586.jpg",
    "product_name": "Laser Etched Black Granite Headstone",
    "design_stampid": "1713512573586",
    "design_price": 3023.97,
    "design_productid": "4",
    "design_orientation": "landscape",
    "design_shape": "Serpentine",
    "design_texture": "src\/granites\/forever2\/l\/18.jpg",
    "design_width": "660.3999999999997",
    "design_height": "660.3999999999997",
    "design_name": "ISAIAH ISAAC H",
    "ml_language": "English",
    "ml_style": "Laser Etched Black Granite",
    "ml_type": "Headstone",
    "ml_motif": "Religious",
    "ml_tags": "SO MUCH OF ISAIAH ISAAC HARTLEY 2000 - 2023 Music was the voice of his soul YOU IN OUR HEARTS May you find some comfort here. You're in the arms of the angel -We'll be together again, \"Zaya\""
}